nfl_data_loader/__init__.py
nfl_data_loader/api/__init__.py
nfl_data_loader/api/feature_stores/__init__.py
nfl_data_loader/api/feature_stores/events/__init__.py
nfl_data_loader/api/feature_stores/events/events.py
nfl_data_loader/api/feature_stores/fantasy/__init__.py
nfl_data_loader/api/feature_stores/fantasy/fantasy.py
nfl_data_loader/api/feature_stores/players/__init__.py
nfl_data_loader/api/feature_stores/players/player_regular_season_game.py
nfl_data_loader/api/loaders/__init__.py
nfl_data_loader/api/loaders/event/__init__.py
nfl_data_loader/api/sources/__init__.py
nfl_data_loader/api/sources/events/__init__.py
nfl_data_loader/api/sources/events/elo/__init__.py
nfl_data_loader/api/sources/events/elo/elo.py
nfl_data_loader/api/sources/events/games/__init__.py
nfl_data_loader/api/sources/events/games/games.py
nfl_data_loader/api/sources/events/pbp/__init__.py
nfl_data_loader/api/sources/events/pbp/pbp.py
nfl_data_loader/api/sources/players/__init__.py
nfl_data_loader/api/sources/players/adv/__init__.py
nfl_data_loader/api/sources/players/adv/av/__init__.py
nfl_data_loader/api/sources/players/adv/av/av.py
nfl_data_loader/api/sources/players/adv/fantasy/__init__.py
nfl_data_loader/api/sources/players/adv/fantasy/projections.py
nfl_data_loader/api/sources/players/adv/fantasy/ranks.py
nfl_data_loader/api/sources/players/adv/fantasy/watson.py
nfl_data_loader/api/sources/players/adv/madden/__init__.py
nfl_data_loader/api/sources/players/adv/madden/madden.py
nfl_data_loader/api/sources/players/adv/ngs/__init__.py
nfl_data_loader/api/sources/players/adv/ngs/ngs.py
nfl_data_loader/api/sources/players/adv/props/__init__.py
nfl_data_loader/api/sources/players/adv/props/player_props.py
nfl_data_loader/api/sources/players/adv/qbr/__init__.py
nfl_data_loader/api/sources/players/adv/qbr/qbr.py
nfl_data_loader/api/sources/players/boxscores/__init__.py
nfl_data_loader/api/sources/players/boxscores/boxscores.py
nfl_data_loader/api/sources/players/general/__init__.py
nfl_data_loader-0.0.14.dist-info/METADATA
nfl_data_loader-0.0.14.dist-info/WHEEL
nfl_data_loader-0.0.14.dist-info/top_level.txt
nfl_data_loader-0.0.14.dist-info/RECORD
