Metadata-Version: 2.4
Name: nfl-data-loader
Version: 0.0.14
Summary: A Python interface for various NFL data sources
Author-email: TheEdgePredictor <theedgepredictor@gmail.com>
Project-URL: Repository, https://github.com/theedgepredictor/nfl-data-loader
Project-URL: Homepage, https://github.com/theedgepredictor/nfl-data-loader
Project-URL: Issues, https://github.com/theedgepredictor/nfl-data-loader/issues
Keywords: data science,sports,NFL
Classifier: Programming Language :: Python :: 3
Classifier: License :: OSI Approved :: MIT License
Classifier: Operating System :: OS Independent
Requires-Python: >=3.8
Requires-Dist: pydantic>2.0.0
Requires-Dist: requests==2.31.0
Requires-Dist: numpy>=1.26.4
Requires-Dist: pandas>=2.2.0
Requires-Dist: pyarrow
Requires-Dist: openpyxl>=3.1.5
Requires-Dist: beautifulsoup4>=4.12.3
Requires-Dist: rapidfuzz
Requires-Dist: espn-api-orm
Requires-Dist: scikit-learn
Requires-Dist: pyreadr
Provides-Extra: test
Requires-Dist: pytest>7.0.0; extra == "test"
